Workbook

Sheet Overview
A1: Section | D1: Value | G1: Unit
A3: Implementation - Total hours | D3: =SUM('Implementation Tasks'!G3:I49) -> 138 | G3: h
A5: Implementation - Total mandays | D5: =SUM('Implementation Tasks'!M3:O50) -> 17.25 | G5: days
A7: Implementation - Total cost | D7: =SUM('Implementation Tasks'!J3:L50) -> 49562.5 | G7: CZK
A9: Hardware price | D9: =SUM('Hardware Price'!J3:L26) -> 907 | G9: CZK
A11: Non-impl. Overhead - cost | D11: =SUM('Non-Implementation Tasks'!J3:L26) -> 60487.5 | G11: CZK
A13: Annual operating costs | D13: =SUM('Yearly Payments'!J3:L11) -> 37500 | G13: CZK
A15: Hourly rate (with VAT) | D15: {=SUM('Staffing & Resources'!G3:I10*'Staffing & Resources'!J3:L10)} -> 403.75 | G15: CZK
A17: 5-year total price | D17: =SUM(D7:F12,D13*4) -> 260957 | G17: CZK

Sheet Implementation Tasks
A1: Category | D1: Task | G1: Hours | J1: Cost (CZK) | M1: Mandays
A3: Hardware | D3: Install Pi into the case | G3: 2 | J3: {=SUM(G3*'Staffing & Resources'!$J$3:$L$4)} -> 750 | M3: =G3/$S$4 -> 0.25
S4: 8
A5: Hardware | D5: Install sensors | G5: 2 | J5: {=SUM(G5*'Staffing & Resources'!$J$3:$L$4)} -> 750 | M5: =G5/$S$4 -> 0.25
A7: Hardware | D7: Install bluetooth interface | G7: 2 | J7: {=SUM(G7*'Staffing & Resources'!$J$3:$L$4)} -> 750 | M7: =G7/$S$4 -> 0.25
A9: Hardware | D9: OS installation | G9: 4 | J9: {=SUM(G9*'Staffing & Resources'!$J$3:$L$4)} -> 1500 | M9: =G9/$S$4 -> 0.5
A11: Development | D11: Environment set up | G11: 20 | J11: {=SUM(G11*'Staffing & Resources'!$J$3:$L$4)} -> 7500 | M11: =G11/$S$4 -> 2.5
A13: Development | D13: Design case | G13: 10 | J13: {=SUM(G13*'Staffing & Resources'!$J$3:$L$4)} -> 3750 | M13: =G13/$S$4 -> 1.25
A15: Software Backend | D15: App skeleton | G15: 5 | J15: {=SUM(G15*'Staffing & Resources'!$J$3:$L$4)} -> 1875 | M15: =G15/$S$4 -> 0.625
A17: Software Backend | D17: App bluetooth | G17: 5 | J17: {=SUM(G17*'Staffing & Resources'!$J$3:$L$4)} -> 1875 | M17: =G17/$S$4 -> 0.625
A19: Software Backend | D19: Data retrieval | G19: 2 | J19: {=SUM(G19*'Staffing & Resources'!$J$3:$L$4)} -> 750 | M19: =G19/$S$4 -> 0.25
A21: Software Backend | D21: Decryption | G21: 2 | J21: {=SUM(G21*'Staffing & Resources'!$J$3:$L$4)} -> 750 | M21: =G21/$S$4 -> 0.25
A23: Software Backend | D23: Data transformation | G23: 2 | J23: {=SUM(G23*'Staffing & Resources'!$J$3:$L$4)} -> 750 | M23: =G23/$S$4 -> 0.25
A25: Software Backend | D25: Data collection | G25: 5 | J25: {=SUM(G25*'Staffing & Resources'!$J$3:$L$4)} -> 1875 | M25: =G25/$S$4 -> 0.625
A27: Software Backend | D27: Encryption | G27: 2 | J27: {=SUM(G27*'Staffing & Resources'!$J$3:$L$4)} -> 750 | M27: =G27/$S$4 -> 0.25
... A35: Software Frontend | D35: Settings menu | G35: 5 | J35: {=SUM(G35*'Staffing & Resources'!$J$3:$L$4)} -> 1875 | M35: =G35/$S$4 -> 0.625
A37: Testing | D37: Functional test | G37: 10 | J37: {=SUM(G37*'Staffing & Resources'!$J$5:$L$6)} -> 3125 | M37: =G37/$S$4 -> 1.25
A39: Testing | D39: Non-functional tests | G39: 10 | J39: {=SUM(G39*'Staffing & Resources'!$J$5:$L$6)} -> 3125 | M39: =G39/$S$4 -> 1.25
Q40: testing | R40: 65 | T40: =R40/T43 -> 22.887324
A41: Testing | D41: Scenario tests | G41: 15 | J41: {=SUM(G41*'Staffing & Resources'!$J$5:$L$6)} -> 4687.5 | M41: =G41/$S$4 -> 1.875 | Q41: SW | R41: 153 | T41: =R41/T43 -> 53.873239
Q42: admin | R42: 66 | T42: =R42/T43 -> 23.239437
R43: =SUM(R40,R41,R42) -> 284 | T43: =284/100 -> 2.84 | U43: =SUM(T40,T41,T42) -> 100
D49: -

Sheet Non-Implementation Tasks
A1: Category | D1: Task | G1: Hours | J1: Cost (CZK) | M1: Mandays
A3: Administration | D3: Team meetings | G3: 30 | J3: =SUM(G3*Overview!$D$15) -> 12112.5 | M3: =G3/8 -> 3.75
A5: Administration | D5: Client meetings | G5: 6 | J5: {=SUM(G5*'Staffing & Resources'!J7:L8)} -> 3375 | M5: =G5/8 -> 0.75
A7: Administration | D7: SRS | G7: 40 | J7: {=SUM(G7*'Staffing & Resources'!$J$7:$L$8)} -> 22500 | M7: =G7/8 -> 5
A9: Administration | D9: Bussiness plan | G9: 10 | J9: {=SUM(G9*'Staffing & Resources'!$J$7:$L$8)} -> 5625 | M9: =G9/8 -> 1.25
A11: Documentation | D11: User manual | G11: 10 | J11: {=SUM(G11*'Staffing & Resources'!$J$7:$L$8)} -> 5625 | M11: =G11/8 -> 1.25
A13: Documentation | D13: Troubleshooting guides | G13: 10 | J13: {=SUM(G13*'Staffing & Resources'!$J$7:$L$8)} -> 5625 | M13: =G13/8 -> 1.25
A15: Documentation | D15: Technical documentation | G15: 10 | J15: {=SUM(G15*'Staffing & Resources'!$J$7:$L$8)} -> 5625 | M15: =G15/8 -> 1.25

Sheet Hardware Price
A1: Component | D1: Unit price + VAT | G1: Qty | J1: Total | M1: URL | P1: Date of price check
A3: Raspberry Pi Zero 2 W | D3: 419 | G3: 1 | J3: =D3*G3 -> 419 | M3: https://rpishop.cz/raspberry-pi-zero/4311-raspberry-pi-zero-2-w.html | P3: 23.3.2026
A5: Waveshare Laser Sensor | D5: 230 | G5: 1 | J5: =D5*G5 -> 230 | M5: https://www.waveshare.com/laser-sensor.htm | P5: 23.3.2026
A7: Ultrasound sensor HC-SR04 | D7: 39 | G7: 2 | J7: =D7*G7 -> 78 | M7: https://rpishop.cz/vzdalenost/815-ultrazvukovy-senzor-hc-sr04.html | P7: 23.3.2026
A9: Time-of-flight sensor VL53LDK | D9: 90 | G9: 2 | J9: =D9*G9 -> 180 | M9: https://allegro.cz/produkt/czujnik-odlegosci-vl53l0x-49792d4c-b92b-4d7e-b4a2-6177db786a88?offerId=9363139945&utm_feed=712e6653-4749-4512-b084-b6e297fc9e0b&utm_source=google&utm_medium=cpc&utm_campaign=CZ%3EElectro%3EHome-electro%3E3P%3EPMAX&ev_campaign_id=20035822444&gad | P9: 23.3.2026

Sheet Staffing & Resources
A1: Role | D1: Salary / month | G1: Utilisation | J1: Hrly cost
A3: SW Engineer Junior | D3: 60000 | G3: 0.54 | J3: =D3/160 -> 375
A5: Tester | D5: 50000 | G5: 0.23 | J5: =D5/160 -> 312.5
A7: Team leader | D7: 90000 | G7: 0.23 | J7: =D7/160 -> 562.5

Sheet Yearly Payments
A1: Cost Item | D1: Hours annualy | G1: Staff member | J1: Annual Cost
A3: Maintanence | D3: 100 | G3: SW Engineer Junior | J3: =D3*'Staffing & Resources'!J3 -> 37500

Sheet Business Plan
